<?xml version="1.0" encoding="UTF-8"?>
<mets:structMap xmlns:mets="http://www.loc.gov/METS/" LABEL="ldpd.ggva.NYDA89-F443">
   <mets:div ORDER="1"
             CONTENTIDS="NYDA.1960.001.00474"
             LABEL="Foundation plan ; detail drawings of -- footing for kitchen chimney, footing for living rm, chimney, section thro' wall : 1."/>
   <mets:div ORDER="2"
             CONTENTIDS="NYDA.1960.001.00475"
             LABEL="Foundation plan ; detail drawings of -- footings for kitchen chimney, section thro' wall : 1."/>
   <mets:div ORDER="3"
             CONTENTIDS="NYDA.1960.001.00476"
             LABEL="First floor plan : 2."/>
   <mets:div ORDER="4"
             CONTENTIDS="NYDA.1960.001.00492"
             LABEL="Amended drawing showing portion of first floor plan : No. 1A."/>
   <mets:div ORDER="5"
             CONTENTIDS="NYDA.1960.001.00477"
             LABEL="Second floor plan : 3."/>
   <mets:div ORDER="6"
             CONTENTIDS="NYDA.1960.001.00493"
             LABEL="Amended drawing showing portion of 2nd floor plan : No. 1b."/>
   <mets:div ORDER="7"
             CONTENTIDS="NYDA.1960.001.00478"
             LABEL="East elevation : 4."/>
   <mets:div ORDER="8"
             CONTENTIDS="NYDA.1960.001.00479"
             LABEL="North elevation : 5."/>
   <mets:div ORDER="9"
             CONTENTIDS="NYDA.1960.001.00480"
             LABEL="West elevation : 6."/>
   <mets:div ORDER="10"
             CONTENTIDS="NYDA.1960.001.00481"
             LABEL="South elevation : 7."/>
   <mets:div ORDER="11"
             CONTENTIDS="NYDA.1960.001.00482"
             LABEL="Details -- section thro' oriel in living room, section thro' stairs, elevation of stairs and hall, elevation of mantel in living rm., section thro' porch : 8."/>
   <mets:div ORDER="12"
             CONTENTIDS="NYDA.1960.001.00494"
             LABEL="Amended drawing showing section through stairs, elevation of stairs and hall : No. 1c."/>
</mets:structMap>
