<?xml version="1.0" encoding="UTF-8"?>
<mets:structMap xmlns:mets="http://www.loc.gov/METS/" LABEL="ldpd.ggva.NYDA89-F406">
   <mets:div ORDER="1"
             CONTENTIDS="NYDA.1960.001.01219"
             LABEL="Foundation plan, section &#34;A-A&#34; : Sheet no. 1,"/>
   <mets:div ORDER="2"
             CONTENTIDS="NYDA.1960.001.01220"
             LABEL="Foundation plan, section &#34;A-A&#34; : Sheet no. 1,"/>
   <mets:div ORDER="3"
             CONTENTIDS="NYDA.1960.001.01221"
             LABEL="Foundation plan, section &#34;A-A&#34; : Sheet no. 1,"/>
   <mets:div ORDER="4"
             CONTENTIDS="NYDA.1960.001.01222"
             LABEL="Foundation plan, section &#34;A-A&#34; : Sheet no. 1,"/>
   <mets:div ORDER="5"
             CONTENTIDS="NYDA.1960.001.01223"
             LABEL="Ground floor plan : Sheet no. 2,"/>
   <mets:div ORDER="6"
             CONTENTIDS="NYDA.1960.001.01224"
             LABEL="Ground floor plan : Sheet no. 2,"/>
   <mets:div ORDER="7"
             CONTENTIDS="NYDA.1960.001.01225"
             LABEL="Ground floor plan : Sheet no. 2,"/>
   <mets:div ORDER="8"
             CONTENTIDS="NYDA.1960.001.01226"
             LABEL="East elevation ; west elevation ; interior elevations -- bedroom #3 north side and south side ; den east side, south side and west side : Sheet no. 3,"/>
   <mets:div ORDER="9"
             CONTENTIDS="NYDA.1960.001.01227"
             LABEL="East elevation ; west elevation ; interior elevations -- bedroom #3 north side and south side and west side : Sheet no. 3,"/>
   <mets:div ORDER="10"
             CONTENTIDS="NYDA.1960.001.01228"
             LABEL="Elevations -- court east side, court south side, south sdie of nursery, north side of dining r'm, south side of dining r'm, west side of dining r'm, east side of dining r'm, east side of hall, east side of living r'm, west side of living r'm : Sheet no. 4,"/>
   <mets:div ORDER="11"
             CONTENTIDS="NYDA.1960.001.01229"
             LABEL="Elevations -- court east side, court south side, south side of nursery, north side of dining r'm, south side of dining r'm, end view of mantel, east side of living r'm, west side of living r'm : Sheet no. 4,"/>
   <mets:div ORDER="12"
             CONTENTIDS="NYDA.1960.001.01230"
             LABEL="Front door in elevation and full size section : Sheet no. 1."/>
   <mets:div ORDER="13"
             CONTENTIDS="NYDA.1960.001.01231"
             LABEL="Garage -- plan, end elevation, front elevation with section through wall : Sheet no. 1,"/>
   <mets:div ORDER="14"
             CONTENTIDS="NYDA.1960.001.01232"
             LABEL="Garage -- plan, end elevation, front elevation with section through wall : Sheet no. 1,"/>
   <mets:div ORDER="15"
             CONTENTIDS="NYDA.1960.001.01233"
             LABEL="Garage -- plan, end elevation, front elevation with section through wall : Sheet no. 1,"/>
   <mets:div ORDER="16"
             CONTENTIDS="NYDA.1960.001.01234"
             LABEL="Garage -- plan, end elevation, front elevation with section through wall : Sheet no. 1,"/>
   <mets:div ORDER="17"
             CONTENTIDS="NYDA.1960.001.01235"
             LABEL="Garage -- plan, end elevation, front elevation with section through wall : Sheet no. 1,"/>
   <mets:div ORDER="18"
             CONTENTIDS="NYDA.1960.001.01236"
             LABEL="Unidentified rough sketches with notes."/>
</mets:structMap>
